edgeutils/__init__.py
edgeutils/db_conn.py
edgeutils/downloader.py
edgeutils/obj_conn.py
edgeutils-0.1.dist-info/DESCRIPTION.rst
edgeutils-0.1.dist-info/METADATA
edgeutils-0.1.dist-info/RECORD
edgeutils-0.1.dist-info/WHEEL
edgeutils-0.1.dist-info/metadata.json
edgeutils-0.1.dist-info/top_level.txt
